[
  {
    "text": "Artikel 1.1 (begripsbepalingen)\n(Bron: Hoofdstuk 1. Algemene bepalingen, Afdeling 1.1. Algemeen)\n\nBijlage I bevat begripsbepalingen voor de toepassing van dit besluit.",
    "metadata": {
      "document_type": "BBL",
      "bwb_identifier": "BWBR0041297",
      "version_date": "2025-07-01",
      "artikel_nummer": "1.1",
      "artikel_label": "Artikel 1.1",
      "artikel_titel": "(begripsbepalingen)",
      "hoofdstuk_nr": "1",
      "hoofdstuk_titel": "Algemene bepalingen",
      "hoofdstuk": "Hoofdstuk 1. Algemene bepalingen",
      "afdeling_nr": "1.1",
      "afdeling_titel": "Algemeen",
      "afdeling": "Afdeling 1.1. Algemeen",
      "leden_count": 1,
      "source_url": "https://wetten.overheid.nl/BWBR0041297/2025-07-01",
      "chunk_type": "artikel",
      "processed_at": "2025-11-03T16:46:24.521009"
    }
  },
  {
    "text": "Artikel 1.1a (grondslag)\n(Bron: Hoofdstuk 1. Algemene bepalingen, Afdeling 1.1. Algemeen)\n\nLid 1. Dit besluit berust op de artikelen 4.3, eerste lid, 5.1, 16.1, derde lid, en 23.1 van de wet.\n\nLid 2. Dit besluit berust ook op de artikelen 119 en 119a van de Woningwet.",
    "metadata": {
      "document_type": "BBL",
      "bwb_identifier": "BWBR0041297",
      "version_date": "2025-07-01",
      "artikel_nummer": "1.1a",
      "artikel_label": "Artikel 1.1a",
      "artikel_titel": "(grondslag)",
      "hoofdstuk_nr": "1",
      "hoofdstuk_titel": "Algemene bepalingen",
      "hoofdstuk": "Hoofdstuk 1. Algemene bepalingen",
      "afdeling_nr": "1.1",
      "afdeling_titel": "Algemeen",
      "afdeling": "Afdeling 1.1. Algemeen",
      "leden_count": 2,
      "source_url": "https://wetten.overheid.nl/BWBR0041297/2025-07-01",
      "chunk_type": "artikel",
      "processed_at": "2025-11-03T16:46:24.521030"
    }
  },
  {
    "text": "Artikel 1.2 (wederzijdse erkenning)\n(Bron: Hoofdstuk 1. Algemene bepalingen, Afdeling 1.2. Internationaalrechtelijke verplichtingen)\n\nMet een kwaliteitsverklaring bouw, certificaat, keuring of norm als bedoeld in dit besluit wordt gelijkgesteld een kwaliteitsverklaring bouw, certificaat, keuring of norm, afgegeven, uitgevoerd of goedgekeurd door een daartoe bevoegde onafhankelijke instelling in een andere lidstaat van de Europese Unie of in een staat die geen lidstaat van de Europese Unie is en partij is bij een verdrag dat Nederland bindt, met een beschermingsniveau dat ten minste gelijkwaardig is aan het niveau dat met de nationale eisen wordt nagestreefd.",
    "metadata": {
      "document_type": "BBL",
      "bwb_identifier": "BWBR0041297",
      "version_date": "2025-07-01",
      "artikel_nummer": "1.2",
      "artikel_label": "Artikel 1.2",
      "artikel_titel": "(wederzijdse erkenning)",
      "hoofdstuk_nr": "1",
      "hoofdstuk_titel": "Algemene bepalingen",
      "hoofdstuk": "Hoofdstuk 1. Algemene bepalingen",
      "afdeling_nr": "1.2",
      "afdeling_titel": "Internationaalrechtelijke verplichtingen",
      "afdeling": "Afdeling 1.2. Internationaalrechtelijke verplichtingen",
      "leden_count": 1,
      "source_url": "https://wetten.overheid.nl/BWBR0041297/2025-07-01",
      "chunk_type": "artikel",
      "processed_at": "2025-11-03T16:46:24.521056"
    }
  },
  {
    "text": "Artikel 2.1 (toepassingsbereik: activiteiten)\n(Bron: Hoofdstuk 2. Algemene bepalingen voor bouwwerken, Afdeling 2.1. Algemeen)\n\nDit hoofdstuk is van toepassing op bouwwerken.",
    "metadata": {
      "document_type": "BBL",
      "bwb_identifier": "BWBR0041297",
      "version_date": "2025-07-01",
      "artikel_nummer": "2.1",
      "artikel_label": "Artikel 2.1",
      "artikel_titel": "(toepassingsbereik: activiteiten)",
      "hoofdstuk_nr": "2",
      "hoofdstuk_titel": "Algemene bepalingen voor bouwwerken",
      "hoofdstuk": "Hoofdstuk 2. Algemene bepalingen voor bouwwerken",
      "afdeling_nr": "2.1",
      "afdeling_titel": "Algemeen",
      "afdeling": "Afdeling 2.1. Algemeen",
      "leden_count": 1,
      "source_url": "https://wetten.overheid.nl/BWBR0041297/2025-07-01",
      "chunk_type": "artikel",
      "processed_at": "2025-11-03T16:46:24.521059"
    }
  },
  {
    "text": "Artikel 2.2 (bevoegd gezag)\n(Bron: Hoofdstuk 2. Algemene bepalingen voor bouwwerken, Afdeling 2.1. Algemeen)\n\nLid 1. Het college van burgemeester en wethouders is het bevoegd gezag: waaraan een melding wordt gedaan; dat een maatwerkvoorschrift kan stellen; en dat beslist op een aanvraag om toestemming tot het treffen van een gelijkwaardige maatregel.\n\nLid 2. In afwijking van het eerste lid zijn voor een activiteit als bedoeld in dit besluit, die wordt verricht op dezelfde locatie als een activiteit als bedoeld in afdeling 3.3 van het Besluit activiteiten leefomgeving, waarvoor een door gedeputeerde staten eerder verleende omgevingsvergunning geldt, gedeputeerde staten het bevoegd gezag voor de in het eerste lid bedoelde handelingen.",
    "metadata": {
      "document_type": "BBL",
      "bwb_identifier": "BWBR0041297",
      "version_date": "2025-07-01",
      "artikel_nummer": "2.2",
      "artikel_label": "Artikel 2.2",
      "artikel_titel": "(bevoegd gezag)",
      "hoofdstuk_nr": "2",
      "hoofdstuk_titel": "Algemene bepalingen voor bouwwerken",
      "hoofdstuk": "Hoofdstuk 2. Algemene bepalingen voor bouwwerken",
      "afdeling_nr": "2.1",
      "afdeling_titel": "Algemeen",
      "afdeling": "Afdeling 2.1. Algemeen",
      "leden_count": 2,
      "source_url": "https://wetten.overheid.nl/BWBR0041297/2025-07-01",
      "chunk_type": "artikel",
      "processed_at": "2025-11-03T16:46:24.521062"
    }
  },
  {
    "text": "Artikel 2.3 (maatwerkregels)\n(Bron: Hoofdstuk 2. Algemene bepalingen voor bouwwerken, Afdeling 2.1. Algemeen)\n\nEen maatwerkregel wordt in het omgevingsplan gesteld.",
    "metadata": {
      "document_type": "BBL",
      "bwb_identifier": "BWBR0041297",
      "version_date": "2025-07-01",
      "artikel_nummer": "2.3",
      "artikel_label": "Artikel 2.3",
      "artikel_titel": "(maatwerkregels)",
      "hoofdstuk_nr": "2",
      "hoofdstuk_titel": "Algemene bepalingen voor bouwwerken",
      "hoofdstuk": "Hoofdstuk 2. Algemene bepalingen voor bouwwerken",
      "afdeling_nr": "2.1",
      "afdeling_titel": "Algemeen",
      "afdeling": "Afdeling 2.1. Algemeen",
      "leden_count": 1,
      "source_url": "https://wetten.overheid.nl/BWBR0041297/2025-07-01",
      "chunk_type": "artikel",
      "processed_at": "2025-11-03T16:46:24.521065"
    }
  },
  {
    "text": "Artikel 2.4 (gelijkwaardigheid bij melding of vergunningvrije activiteit)\n(Bron: Hoofdstuk 2. Algemene bepalingen voor bouwwerken, Afdeling 2.1. Algemeen)\n\nLid 1. Als een gelijkwaardige maatregel betrekking heeft op een activiteit waarvoor in dit besluit een melding is voorgeschreven: is voorafgaande toestemming als bedoeld in artikel 4.7 van de wet niet vereist; en is het verboden deze maatregel te treffen zonder voorafgaande melding.\n\nLid 2. Als een gelijkwaardige maatregel betrekking heeft op een activiteit waarvoor op grond van de wet geen omgevingsvergunning is vereist en waarvoor in dit besluit geen melding is voorgeschreven, is voorafgaande toestemming als bedoeld in artikel 4.7 van de wet niet vereist.",
    "metadata": {
      "document_type": "BBL",
      "bwb_identifier": "BWBR0041297",
      "version_date": "2025-07-01",
      "artikel_nummer": "2.4",
      "artikel_label": "Artikel 2.4",
      "artikel_titel": "(gelijkwaardigheid bij melding of vergunningvrije activiteit)",
      "hoofdstuk_nr": "2",
      "hoofdstuk_titel": "Algemene bepalingen voor bouwwerken",
      "hoofdstuk": "Hoofdstuk 2. Algemene bepalingen voor bouwwerken",
      "afdeling_nr": "2.1",
      "afdeling_titel": "Algemeen",
      "afdeling": "Afdeling 2.1. Algemeen",
      "leden_count": 2,
      "source_url": "https://wetten.overheid.nl/BWBR0041297/2025-07-01",
      "chunk_type": "artikel",
      "processed_at": "2025-11-03T16:46:24.521068"
    }
  },
  {
    "text": "Artikel 2.5 (instandhouden gelijkwaardige maatregel)\n(Bron: Hoofdstuk 2. Algemene bepalingen voor bouwwerken, Afdeling 2.1. Algemeen)\n\nEen gelijkwaardige maatregel die betrekking heeft op een in de hoofdstukken 3 tot en met 6 gestelde regel wordt bij het gebruik van het bouwwerk in stand gehouden.",
    "metadata": {
      "document_type": "BBL",
      "bwb_identifier": "BWBR0041297",
      "version_date": "2025-07-01",
      "artikel_nummer": "2.5",
      "artikel_label": "Artikel 2.5",
      "artikel_titel": "(instandhouden gelijkwaardige maatregel)",
      "hoofdstuk_nr": "2",
      "hoofdstuk_titel": "Algemene bepalingen voor bouwwerken",
      "hoofdstuk": "Hoofdstuk 2. Algemene bepalingen voor bouwwerken",
      "afdeling_nr": "2.1",
      "afdeling_titel": "Algemeen",
      "afdeling": "Afdeling 2.1. Algemeen",
      "leden_count": 1,
      "source_url": "https://wetten.overheid.nl/BWBR0041297/2025-07-01",
      "chunk_type": "artikel",
      "processed_at": "2025-11-03T16:46:24.521070"
    }
  },
  {
    "text": "Artikel 2.6 (specifieke zorgplicht: bouwwerkinstallatie)\n(Bron: Hoofdstuk 2. Algemene bepalingen voor bouwwerken, Afdeling 2.1. Algemeen)\n\nDe eigenaar van het bouwwerk of degene die uit anderen hoofde bevoegd is tot het treffen van voorzieningen aan dat bouwwerk draagt er zorg voor dat een krachtens de wet aanwezige bouwwerkinstallatie: functioneert in overeenstemming met de op die installatie van toepassing zijnde regels; adequaat wordt beheerd, onderhouden en gecontroleerd; en zodanig wordt gebruikt dat geen gevaar voor de gezondheid of de veiligheid ontstaat of voortduurt.",
    "metadata": {
      "document_type": "BBL",
      "bwb_identifier": "BWBR0041297",
      "version_date": "2025-07-01",
      "artikel_nummer": "2.6",
      "artikel_label": "Artikel 2.6",
      "artikel_titel": "(specifieke zorgplicht: bouwwerkinstallatie)",
      "hoofdstuk_nr": "2",
      "hoofdstuk_titel": "Algemene bepalingen voor bouwwerken",
      "hoofdstuk": "Hoofdstuk 2. Algemene bepalingen voor bouwwerken",
      "afdeling_nr": "2.1",
      "afdeling_titel": "Algemeen",
      "afdeling": "Afdeling 2.1. Algemeen",
      "leden_count": 1,
      "source_url": "https://wetten.overheid.nl/BWBR0041297/2025-07-01",
      "chunk_type": "artikel",
      "processed_at": "2025-11-03T16:46:24.521073"
    }
  },
  {
    "text": "Artikel 2.7 (gemeenschappelijk en gezamenlijk)\n(Bron: Hoofdstuk 2. Algemene bepalingen voor bouwwerken, Afdeling 2.1. Algemeen)\n\nLid 1. Voor de toepassing van een in de hoofdstukken 3 tot en met 6 gestelde regel is een bouwwerk, een ruimte, een voorziening, of een gedeelte daarvan naar keuze gemeenschappelijk of niet-gemeenschappelijk, tenzij voor een regel anders is aangegeven.\n\nLid 2. Voor de toepassing van een in de hoofdstukken 3 tot en met 6 gestelde regel wordt een gedeelte van een bouwwerk, een ruimte of een voorziening die ten dienste staat van meer dan een gebruiksfunctie, aangemerkt als gemeenschappelijk. Dit gedeelte, deze ruimte of deze voorziening maakt, met uitzondering van een nevengebruiksfunctie, voor de toepassing van deze hoofdstukken deel uit van alle daarop aangewezen gebruiksfuncties.\n\nLid 3. Voor de toepassing van een in de hoofdstukken 3 tot en met 6 gestelde regel wordt een gedeelte van een woonfunctie, een celfunctie of een logiesfunctie of een ruimte of voorziening die ten dienste staat van die gebruiksfunctie, gebruikt door meer dan een wooneenheid, celeenheid of logiesverblijf in die gebruiksfunctie, aangemerkt als gezamenlijk.",
    "metadata": {
      "document_type": "BBL",
      "bwb_identifier": "BWBR0041297",
      "version_date": "2025-07-01",
      "artikel_nummer": "2.7",
      "artikel_label": "Artikel 2.7",
      "artikel_titel": "(gemeenschappelijk en gezamenlijk)",
      "hoofdstuk_nr": "2",
      "hoofdstuk_titel": "Algemene bepalingen voor bouwwerken",
      "hoofdstuk": "Hoofdstuk 2. Algemene bepalingen voor bouwwerken",
      "afdeling_nr": "2.1",
      "afdeling_titel": "Algemeen",
      "afdeling": "Afdeling 2.1. Algemeen",
      "leden_count": 3,
      "source_url": "https://wetten.overheid.nl/BWBR0041297/2025-07-01",
      "chunk_type": "artikel",
      "processed_at": "2025-11-03T16:46:24.521081"
    }
  }
]